printu/__init__.py
printu/cli.py
printu/printu.py
printu-0.1.2.dist-info/entry_points.txt
printu-0.1.2.dist-info/WHEEL
printu-0.1.2.dist-info/METADATA
printu-0.1.2.dist-info/RECORD
